cicd/__init__.py
cicd-0.0.1.dist-info/LICENSE
cicd-0.0.1.dist-info/METADATA
cicd-0.0.1.dist-info/WHEEL
cicd-0.0.1.dist-info/top_level.txt
cicd-0.0.1.dist-info/RECORD
