Metadata-Version: 2.1
Name: cicd
Version: 0.0.1
Summary: ok
Home-page: https://github.com/private_repo/cicd
Author: slipper
Author-email: r2fscg@gmail.com
License: UNKNOWN
Platform: UNKNOWN
Classifier: Programming Language :: Python :: 3
Classifier: License :: OSI Approved :: MIT License
Classifier: Operating System :: OS Independent
License-File: LICENSE
Requires-Dist: codefast
Requires-Dist: authc
Requires-Dist: jieba
Requires-Dist: fastapi
Requires-Dist: uvicorn
Requires-Dist: expiringdict
Requires-Dist: redis
Requires-Dist: pika
Requires-Dist: hashids
